Teleios/GEMLib.py
Teleios/_GEMLib.exp
Teleios/_GEMLib.lib
Teleios/_GEMLib.pyd
Teleios/_GEMLib.pyd.manifest
Teleios/__init__.py
GEMLibrary_windows-0.3.2.dist-info/LICENSE
GEMLibrary_windows-0.3.2.dist-info/METADATA
GEMLibrary_windows-0.3.2.dist-info/WHEEL
GEMLibrary_windows-0.3.2.dist-info/top_level.txt
GEMLibrary_windows-0.3.2.dist-info/RECORD
