Metadata-Version: 2.1
Name: GEMLibrary-windows
Version: 0.3.2
Summary: GEM Derivatives Library
Home-page: UNKNOWN
Author: Kevin Morgan
Author-email: KMorgan@teleioscommodities.com
License: UNKNOWN
Platform: UNKNOWN
Classifier: Programming Language :: Python :: 3
Classifier: License :: Other/Proprietary License
Classifier: Operating System :: Microsoft :: Windows :: Windows 10
Requires-Python: >=3.6
